supertokens_python/__init__.py
supertokens_python/async_to_sync_wrapper.py
supertokens_python/auth_utils.py
supertokens_python/constants.py
supertokens_python/exceptions.py
supertokens_python/interfaces.py
supertokens_python/logger.py
supertokens_python/normalised_url_domain.py
supertokens_python/normalised_url_path.py
supertokens_python/post_init_callbacks.py
supertokens_python/process_state.py
supertokens_python/py.typed
supertokens_python/querier.py
supertokens_python/recipe_module.py
supertokens_python/supertokens.py
supertokens_python/utils.py
supertokens_python/asyncio/__init__.py
supertokens_python/env/__init__.py
supertokens_python/env/base.py
supertokens_python/env/utils.py
supertokens_python/framework/__init__.py
supertokens_python/framework/request.py
supertokens_python/framework/response.py
supertokens_python/framework/types.py
supertokens_python/framework/django/__init__.py
supertokens_python/framework/django/django_middleware.py
supertokens_python/framework/django/django_request.py
supertokens_python/framework/django/django_response.py
supertokens_python/framework/django/framework.py
supertokens_python/framework/fastapi/__init__.py
supertokens_python/framework/fastapi/fastapi_middleware.py
supertokens_python/framework/fastapi/fastapi_request.py
supertokens_python/framework/fastapi/fastapi_response.py
supertokens_python/framework/fastapi/framework.py
supertokens_python/framework/flask/__init__.py
supertokens_python/framework/flask/flask_middleware.py
supertokens_python/framework/flask/flask_request.py
supertokens_python/framework/flask/flask_response.py
supertokens_python/framework/flask/framework.py
supertokens_python/ingredients/__init__.py
supertokens_python/ingredients/emaildelivery/__init__.py
supertokens_python/ingredients/emaildelivery/types.py
supertokens_python/ingredients/emaildelivery/services/__init__.py
supertokens_python/ingredients/emaildelivery/services/smtp.py
supertokens_python/ingredients/smsdelivery/__init__.py
supertokens_python-0.30.3.dist-info/licenses/LICENSE.md
supertokens_python-0.30.3.dist-info/METADATA
supertokens_python-0.30.3.dist-info/WHEEL
supertokens_python-0.30.3.dist-info/top_level.txt
supertokens_python-0.30.3.dist-info/RECORD
